adder.vhd
library IEEE;
use IEEE.STD_LOGIC_1164.ALL;

entity Adder is
    generic (
        WIDTH : positive -- Width of the adder 
    );
    Port (
        A     : in  std_logic_vector(WIDTH-1 downto 0);      -- First input
        B     : in  std_logic_vector(WIDTH-1 downto 0);      -- Second input
        Cin   : in  std_logic;                               -- Carry input
        Sum   : out std_logic_vector(WIDTH-1 downto 0);      -- Sum output
        Cout  : out std_logic                                -- Carry output
    );
end Adder;

architecture Behavioral of Adder is
begin

    sum_process: process(A, B, Cin)
    variable temp_carry : std_logic;
    begin
        -- Initial carry input
        temp_carry := Cin; 
        for i in 0 to WIDTH-1 loop

            -- Sum bit calculation
            Sum(i) <= A(i) XOR B(i) XOR temp_carry;

            -- Carry calculation for next bit
            temp_carry := (A(i) AND B(i)) OR (temp_carry AND (A(i) XOR B(i))); 
        end loop;

        -- Final carry output
        Cout <= temp_carry; 

    end process sum_process;
end Behavioral;

reg_sol.vhd
--! Project : Register    
--! <br>               
--! Author : Emiliano Sisinni                   
--! <br>               
--! Date : AY2024/2025                          
--! <br>               
--! Company : UniBS                             
--! <br>               
--! File : reg.vhd  
--! <br>               
--! This example illustrates a variety of different register entities. To
--! simulate/synthesize a different entity, change the comments in the reg
--! entity at the bottom of this file.

library ieee;
use ieee.std_logic_1164.all;

-- Entity: reg_async_rst
-- Description: Implements a register with an active high, asynchronous reset.

entity reg_async_rst is
    generic(
        WIDTH : positive
        );
    port(
        clk    : in  std_logic;
        rst    : in  std_logic;
        input  : in  std_logic_vector(WIDTH-1 downto 0);
        output : out std_logic_vector(WIDTH-1 downto 0)
        );
end reg_async_rst;

architecture BHV of reg_async_rst is
begin
    -- GUIDELINE 1 FOR SEQUENTIAL LOGIC: The sensitivity list should
    -- only have clock and reset (if there is an asynchronous reset). It
    -- technically shouldn't hurt anything if you include other signals, but
    -- they are not necessary, can slow down a simulation by needlessly
    -- retriggering the process, and might confuse a bad synthesis tool.
    
    process(clk, rst)
    begin
        -- SYNTHESIS GUIDELINE 2 FOR SEQUENTIAL LOGIC: All sequential logic with
        -- async reset should be described using the following basic structure:
        --
        -- if reset
        --   handle reset 
        -- elsif rising clock edge
        --   specify all non-reset functionality
        -- end if
        --
        -- Do not try to come up with another way of specifying equivalent
        -- behavior. Synthesis tools often require this template.
        --
        -- There are other techniques that will work with some tools, but since
        -- this template works for any form of sequential logic, there is no
        -- need to change it.
        
        if (rst = '0') then
            -- Reset the output to all 0s. The others statement sets all the
            -- bits equal to the specified value. It is part of a more general
            -- aggregation construct that will be discussed in other examples.
            output <= (others => '0');
            
        elsif (rising_edge(clk)) then

            -- SYNTHESIS RULE: Any assignment to a signal on a rising clock
            -- edge will be synthesized as a register, where the LHS is the
            -- output of the register, and the RHS is the input. This might
            -- seem obvious for this simple example, but it is critically
            -- important to remember this rule for bigger examples because
            -- adding or omitting a register is a very common source of bugs.
            -- When we "design the circuit" before writing the code, a huge
            -- part of that design is determining the number of registers.
            -- To ensure that the synthesized circuit has the same number of
            -- registers as our design circuit, we need to understand how
            -- registers get created during synthesis.
            --
            -- Note that variables can be synthesized as either wires or
            -- registers depending on the usage, which will be explained in
            -- later examples.
            output <= input;
        end if;
    end process;
end BHV;


library ieee;
use ieee.std_logic_1164.all;

-- Entity: reg_sync_rst
-- Description: Implements a register with an active high, synchronous reset.

entity reg_sync_rst is
    generic(
        WIDTH : positive
        );
    port(
        clk    : in  std_logic;
        rst    : in  std_logic;
        input  : in  std_logic_vector(WIDTH-1 downto 0);
        output : out std_logic_vector(WIDTH-1 downto 0)
        );
end reg_sync_rst;

architecture BHV of reg_sync_rst is
begin
    -- For a synchronous reset, we only need the clock in the sensitivity list.
    -- However, it doesn't really hurt to include reset because a simulation is
    -- unlikely to be frequently resetting a register, so it probably won't
    -- slow down the simulation much. Also, it won't affect synthesis. 
    process(clk)
    begin
        if (rising_edge(clk)) then
            -- For the synchronous reset, we check the reset on the rising
            -- clock edge.
            if (rst = '0') then
                output <= (others => '0');
            else
                output <= input;
            end if;
        end if;
    end process;
end BHV;


library ieee;
use ieee.std_logic_1164.all;

-- Entity: reg_en_async_rst
-- Description: Implements a register with an enable, and an active high,
-- asynchronous reset. The register holds its value when enable isn't asserted.

entity reg_en_async_rst is
    generic(
        WIDTH : positive
        );
    port(
        clk    : in  std_logic;
        rst    : in  std_logic;
        en     : in  std_logic;
        input  : in  std_logic_vector(WIDTH-1 downto 0);
        output : out std_logic_vector(WIDTH-1 downto 0)
        );
end reg_en_async_rst;

architecture BHV of reg_en_async_rst is
begin
    process(clk, rst)
    begin
        if (rst = '0') then
            output <= (others => '0');
            
        elsif (rising_edge(clk)) then
            -- Here we simply add an if statement to check if enable is
            -- asserted. Note that to comply with my coding guideline,
            -- this has to be done on the rising clock edge since it isn't
            -- related to reset.
            if (en = '1') then
                output <= input;
            end if;
        end if;
    end process;
end BHV;


library ieee;
use ieee.std_logic_1164.all;

-- Entity: reg_en_sync_rst
-- Description: Implements a register with an enable, and an active high,
-- synchronous reset. The register holds its value when enable isn't asserted.

entity reg_en_sync_rst is
    generic(
        WIDTH : positive
        );
    port(
        clk    : in  std_logic;
        rst    : in  std_logic;
        en     : in  std_logic;
        input  : in  std_logic_vector(WIDTH-1 downto 0);
        output : out std_logic_vector(WIDTH-1 downto 0)
        );
end reg_en_sync_rst;


architecture BHV of reg_en_sync_rst is
begin
    process(clk)
    begin
        if (rising_edge(clk)) then
            -- Here we move the reset on the clock edge to make it synchronous
            -- and then have an elsif for the enable. Note that we have to
            -- check the conditions in this order since reset has priority
            -- over the enable.
            if (rst = '0') then
                output <= (others => '0');
            elsif (en = '1') then
                output <= input;
            end if;
        end if;
    end process;
end BHV;





library ieee;
use ieee.std_logic_1164.all;

-- Entity: reg
-- Description: Provides a top-level reigster entity for evaluating all the
-- implementations shown above.

entity reg is
    generic(
        WIDTH : positive := 8
        );
    port(
        clk    : in  std_logic;
        rst    : in  std_logic;
        en     : in  std_logic;
        input  : in  std_logic_vector(WIDTH-1 downto 0);
        output : out std_logic_vector(WIDTH-1 downto 0)
        );
end reg;

architecture default_arch of reg is
begin

    -- INSTRUCTIONS: Uncomment the architecture/entity that you want to
    -- evaluate.

    --U_REG : entity work.reg_async_rst
    U_REG : entity work.reg_sync_rst
        generic map (WIDTH => WIDTH)
        port map (clk    => clk,
                  rst    => rst,
                  input  => input,
                  output => output);



    --U_REG : entity work.reg_en_async_rst
    --U_REG : entity work.reg_en_sync_rst
    --    generic map (WIDTH => WIDTH)
    --    port map (clk    => clk,
    --              rst    => rst,
    --              en     => en,
    --              input  => input,
    --              output => output);



    
end default_arch;

integrator.vhd
--! Project : Integrator    
--! <br>               
--! Author : Marco Corazzina                
--! <br>               
--! Date : 2026                          
--! <br>               
--! Company : UniBS                             
--! <br>               
--! File : integrator.vhd  
--! <br>               
--! Implementation of an integrator to be used inside a CIC filter. 
--! The integrator is a simple accumulator that sums the input signal over time. 


library ieee;
use ieee.std_logic_1164.all;

entity integrator is
    generic(
        WIDTH : positive
        );
    port(
        clk    : in  std_logic;
        rst    : in  std_logic;
		en 	   : in  std_logic;
		Cout   : out std_logic;
        input  : in  std_logic_vector(WIDTH-1 downto 0);
        output : out std_logic_vector(WIDTH-1 downto 0)
        );
end integrator;

architecture Default of integrator is

	component reg_en_async_rst
    	generic (WIDTH: integer);
		port(
			clk    : in  std_logic;
			rst    : in  std_logic;
			en     : in  std_logic;
			input  : in  std_logic_vector(WIDTH-1 downto 0);
			output : out std_logic_vector(WIDTH-1 downto 0)
		);
  	end component;
  
  	component adder
    	generic (WIDTH: integer);
		port( 
			A     : in  std_logic_vector(WIDTH-1 downto 0);      -- First input
        	B     : in  std_logic_vector(WIDTH-1 downto 0);      -- Second input
        	Cin   : in  std_logic;                               -- Carry input
        	Sum   : out std_logic_vector(WIDTH-1 downto 0);      -- Sum output
        	Cout  : out std_logic   
		);
	end component;

	
	signal temp_output : std_logic_vector(WIDTH-1 downto 0);
	signal reg_output : std_logic_vector(WIDTH-1 downto 0);

begin

	reg: reg_en_async_rst
		generic map (WIDTH => WIDTH)
		port map (
			clk => clk,
			rst => rst,
			en => en,
			input => temp_output,
			output => reg_output
		);
	
	add: adder
		generic map (WIDTH => WIDTH)
		port map (
			A => reg_output,
			B => input,
			Cin => '0',				-- If WIDTH is choosen correctly, the carry should never be used, so we can set it to 0 
			Sum => temp_output,
			Cout => Cout 			-- If WIDTH is choosen incorrectly, Cout can be used to detect such an error (Cout = 1)
		);
	
	process(rst, en, temp_output)
	begin
		if rst = '0' then
			output <= (others => '0');
		else
			if en = '1' then
				output <= temp_output;
			end if;
		end if;
	end process;

end Default;

testbench.vhd
--! Project : Carry Look-Ahead Adder    
--! <br>               
--! Author : Emiliano Sisinni                   
--! <br>               
--! Date : AY2024/2025                          
--! <br>               
--! Company : UniBS                             
--! <br>               
--! File : testbench.vhd  

LIBRARY ieee;
USE ieee.std_logic_1164.ALL;

ENTITY testbench IS
END testbench;

ARCHITECTURE behavior OF testbench IS


constant WIDTH  : positive := 4;

-- Component Declaration for the Unit Under Test (UUT)

COMPONENT integrator
    GENERIC(
        WIDTH : positive
        );
    PORT(
        clk     : IN std_logic;
        rst     : IN std_logic;
        en      : IN std_logic;
        input   : IN std_logic_vector(WIDTH-1 downto 0);
        output  : OUT std_logic_vector(WIDTH-1 downto 0);
        Cout    : OUT std_logic
    );
END COMPONENT;


--Inputs
signal input    : std_logic_vector(WIDTH-1 downto 0) := (others => '0');


signal clk_en   : std_logic := '1';

signal en       : std_logic := '1';
signal clk      : std_logic := '0';
signal rst      : std_logic := '0';

--Outputs
signal output   : std_logic_vector(WIDTH-1 downto 0);
signal Cout     : std_logic;

BEGIN

-- Instantiate the Unit Under Test (UUT)
uut: integrator
generic map (WIDTH => WIDTH)
port map (
    clk => clk,
    rst => rst,
    input => input,
    output => output,
    Cout => Cout,
    en => en
);
  -- 50 MHz clock generation
  clk <= not clk and clk_en after 10 ns;

-- Stimulus process
stim_proc: process
begin
  rst   <= '0';
  en    <= '1';
  input <= (others => '0');
  
  wait for 10 ns;
  rst   <= '1';

  input <= "0001";

  wait for 5 ns;
  rst   <= '0';

  wait for 5 ns;
  rst   <= '1';

  wait for 10 ns;
  input <= "0010";

  wait for 20 ns;
  input <= "1001";

  wait for 20 ns;
  input <= "0000";

  wait for 20 ns;
  input <= "1010";
  wait;

end process;

END;

result.vcd
$date
  Sun May 24 15:33:11 2026
$end
$version
  GHDL v0
$end
$timescale
  1 fs
$end
$scope module standard $end
$upscope $end
$scope module std_logic_1164 $end
$upscope $end
$scope module testbench $end
$var reg 4 ! input[3:0] $end
$var reg 1 " clk_en $end
$var reg 1 # en $end
$var reg 1 $ clk $end
$var reg 1 % rst $end
$var reg 4 & output[3:0] $end
$var reg 1 ' cout $end
$scope module uut $end
$var reg 1 ( clk $end
$var reg 1 ) rst $end
$var reg 1 * en $end
$var reg 1 + cout $end
$var reg 4 , input[3:0] $end
$var reg 4 - output[3:0] $end
$var reg 4 . temp_output[3:0] $end
$var reg 4 / reg_output[3:0] $end
$scope module reg $end
$var reg 1 0 clk $end
$var reg 1 1 rst $end
$var reg 1 2 en $end
$var reg 4 3 input[3:0] $end
$var reg 4 4 output[3:0] $end
$upscope $end
$scope module add $end
$var reg 4 5 a[3:0] $end
$var reg 4 6 b[3:0] $end
$var reg 1 7 cin $end
$var reg 4 8 sum[3:0] $end
$var reg 1 9 cout $end
$upscope $end
$upscope $end
$upscope $end
$enddefinitions $end
#0
b0000 !
1"
1#
0$
0%
b0000 &
0'
0(
0)
1*
0+
b0000 ,
b0000 -
b0000 .
b0000 /
00
01
12
b0000 3
b0000 4
b0000 5
b0000 6
07
b0000 8
09
#10000000
b0001 !
1$
1%
b0001 &
1(
1)
b0001 ,
b0001 -
b0001 .
10
11
b0001 3
b0001 6
b0001 8
#15000000
0%
b0000 &
0)
b0000 -
01
#20000000
0$
1%
b0001 &
0(
1)
b0001 -
00
11
#30000000
b0010 !
1$
b0011 &
1(
b0010 ,
b0011 -
b0011 .
b0001 /
10
b0011 3
b0001 4
b0001 5
b0010 6
b0011 8
#40000000
0$
0(
00
#50000000
b1001 !
1$
b1100 &
1(
b1001 ,
b1100 -
b1100 .
b0011 /
10
b1100 3
b0011 4
b0011 5
b1001 6
b1100 8
#60000000
0$
0(
00
#70000000
b0000 !
1$
1(
b0000 ,
b1100 /
10
b1100 4
b1100 5
b0000 6
#80000000
0$
0(
00
#90000000
b1010 !
1$
b0110 &
1'
1(
1+
b1010 ,
b0110 -
b0110 .
10
b0110 3
b1010 6
b0110 8
19
#100000000
0$
0(
00
#110000000
1$
b0000 &
1(
b0000 -
b0000 .
b0110 /
10
b0000 3
b0110 4
b0110 5
b0000 8
#120000000
0$
0(
00
#130000000
1$
b1010 &
0'
1(
0+
b1010 -
b1010 .
b0000 /
10
b1010 3
b0000 4
b0000 5
b1010 8
09
#140000000
0$
0(
00
#150000000
1$
b0100 &
1'
1(
1+
b0100 -
b0100 .
b1010 /
10
b0100 3
b1010 4
b1010 5
b0100 8
19
#160000000
0$
0(
00
#170000000
1$
b1110 &
0'
1(
0+
b1110 -
b1110 .
b0100 /
10
b1110 3
b0100 4
b0100 5
b1110 8
09
#180000000
0$
0(
00
#190000000
1$
b1000 &
1'
1(
1+
b1000 -
b1000 .
b1110 /
10
b1000 3
b1110 4
b1110 5
b1000 8
19
